License.txt
MANIFEST.in
README.txt
setup.cfg
setup.py
TinkerPy.egg-info/PKG-INFO
TinkerPy.egg-info/SOURCES.txt
TinkerPy.egg-info/dependency_links.txt
TinkerPy.egg-info/top_level.txt
TinkerPy.egg-info/zip-safe
tinkerpy/__init__.py
tinkerpy/fsm.py